dominik/__init__.py
dominik/dominik.jpg
dominik/dominik.py
dominik-0.2.2.dist-info/METADATA
dominik-0.2.2.dist-info/WHEEL
dominik-0.2.2.dist-info/entry_points.txt
dominik-0.2.2.dist-info/top_level.txt
dominik-0.2.2.dist-info/RECORD
