Metadata-Version: 2.4
Name: dominik
Version: 0.2.2
Summary: Very serious Windows utility
Requires-Python: >=3.8
